{"stats":{"minecraft:used":{"minecraft:oak_fence":5,"minecraft:enchanting_table":2,"minecraft:iron_shovel":505,"minecraft:oak_sign":3,"minecraft:chest":6,"minecraft:shield":89,"minecraft:stone":38,"minecraft:iron_sword":497,"minecraft:sculk_sensor":4,"minecraft:torch":609,"minecraft:dirt":338,"minecraft:anvil":1,"minecraft:nether_bricks":3,"minecraft:carrot":74,"minecraft:spruce_fence":18,"minecraft:polished_diorite":494,"minecraft:lava_bucket":5,"minecraft:bookshelf":28,"minecraft:red_wool":46,"minecraft:iron_axe":604,"minecraft:green_wool":3,"minecraft:quartz_block":89,"minecraft:cherry_leaves":4,"minecraft:barrel":44,"minecraft:stone_brick_stairs":125,"minecraft:stone_bricks":755,"minecraft:light_gray_wool":262,"minecraft:redstone_lamp":1,"minecraft:written_book":1,"minecraft:goat_horn":36,"minecraft:furnace":12,"minecraft:egg":1,"minecraft:cooked_beef":1,"minecraft:cobbled_deepslate":103,"minecraft:pointed_dripstone":4,"minecraft:wheat_seeds":68,"minecraft:emerald_ore":1,"minecraft:water_bucket":21,"minecraft:spruce_door":1,"minecraft:chorus_fruit":1,"minecraft:stone_pickaxe":79,"minecraft:baked_potato":17,"minecraft:lime_wool":2,"minecraft:oak_planks":44,"minecraft:ender_pearl":2,"minecraft:cherry_planks":151,"minecraft:sugar_cane":69,"minecraft:stonecutter":1,"minecraft:llama_spawn_egg":5,"minecraft:white_wool":98,"minecraft:oak_slab":5,"minecraft:crafting_table":16,"minecraft:light_blue_wool":10,"minecraft:chiseled_quartz_block":68,"minecraft:white_bed":6,"minecraft:dripstone_block":1,"minecraft:oak_log":202,"minecraft:diamond_pickaxe":8,"minecraft:cherry_door":2,"minecraft:bread":89,"minecraft:iron_pickaxe":2681,"minecraft:cherry_sign":2,"minecraft:oak_pressure_plate":1,"minecraft:gravel":5,"minecraft:stone_axe":122,"minecraft:yellow_wool":51,"minecraft:pink_petals":15,"minecraft:fishing_rod":27,"minecraft:cherry_stairs":2,"minecraft:cobblestone":151,"minecraft:bucket":26,"minecraft:andesite":6,"minecraft:oak_boat":1,"minecraft:ice":4,"minecraft:stripped_oak_log":16,"minecraft:warped_button":2,"minecraft:oak_hanging_sign":1,"minecraft:candle":5},"minecraft:crafted":{"minecraft:cherry_planks":420,"minecraft:oak_planks":536,"minecraft:barrel":44,"minecraft:furnace":12,"minecraft:stone":735,"minecraft:iron_boots":1,"minecraft:iron_axe":3,"minecraft:stone_pickaxe":1,"minecraft:chest":7,"minecraft:stone_bricks":1048,"minecraft:wheat":135,"minecraft:oak_slab":114,"minecraft:crafting_table":11,"minecraft:enchanting_table":1,"minecraft:wooden_pickaxe":1,"minecraft:baked_potato":17,"minecraft:iron_helmet":43,"minecraft:iron_sword":2,"minecraft:stone_axe":2,"minecraft:bread":60,"minecraft:air":0,"minecraft:oak_boat":1,"minecraft:stone_brick_stairs":156,"minecraft:iron_chestplate":1,"minecraft:book":1,"minecraft:paper":3,"minecraft:cherry_sign":3,"minecraft:diamond_pickaxe":1,"minecraft:shield":1,"minecraft:stick":208,"minecraft:iron_ingot":555,"minecraft:iron_pickaxe":13,"minecraft:iron_block":3,"minecraft:iron_leggings":1,"minecraft:iron_shovel":3,"minecraft:cherry_door":3,"minecraft:gold_ingot":96,"minecraft:stonecutter":1,"minecraft:anvil":1,"minecraft:torch":608},"minecraft:killed_by":{"minecraft:player":1,"minecraft:enderman":2,"minecraft:skeleton":1},"minecraft:dropped":{"minecraft:wheat_seeds":13,"minecraft:lapis_lazuli":3,"minecraft:chorus_fruit":2,"minecraft:copper_ingot":4,"minecraft:stick":1,"minecraft:flint":2,"minecraft:iron_pickaxe":1,"minecraft:string":10,"minecraft:pink_petals":2,"minecraft:stone_axe":1,"minecraft:sweet_berries":11,"minecraft:iron_nugget":4,"minecraft:stone_sword":1,"minecraft:golden_chestplate":1,"minecraft:raw_copper":4,"minecraft:obsidian":3,"minecraft:pointed_dripstone":16,"minecraft:cherry_sapling":1,"minecraft:rotten_flesh":2,"minecraft:recovery_compass":1,"minecraft:suspicious_stew":1,"minecraft:hay_block":16,"minecraft:spider_eye":2,"minecraft:bow":2,"minecraft:wooden_pickaxe":1,"minecraft:stone_pickaxe":1,"minecraft:written_book":4},"minecraft:mined":{"minecraft:white_bed":7,"minecraft:deepslate_diamond_ore":1,"minecraft:candle":10,"minecraft:jungle_slab":1,"minecraft:sculk_vein":4,"minecraft:cherry_log":106,"minecraft:obsidian":5,"minecraft:nether_bricks":6,"minecraft:granite":3,"minecraft:grass_block":451,"minecraft:pink_stained_glass":1,"minecraft:oak_pressure_plate":1,"minecraft:deepslate_bricks":3,"minecraft:polished_diorite":6,"minecraft:spruce_leaves":6,"minecraft:hay_block":31,"minecraft:redstone_ore":3,"minecraft:carrots":21,"minecraft:barrel":4,"minecraft:iron_ore":442,"minecraft:fire":2,"minecraft:cobbled_deepslate":1,"minecraft:andesite":15,"minecraft:deepslate_lapis_ore":5,"minecraft:enchanting_table":1,"minecraft:gold_block":4,"minecraft:sculk_shrieker":3,"minecraft:bookshelf":1,"minecraft:pointed_dripstone":1,"minecraft:deepslate_iron_ore":82,"minecraft:chorus_plant":2,"minecraft:stone":872,"minecraft:cherry_stairs":2,"minecraft:deepslate_redstone_ore":14,"minecraft:oak_slab":3,"minecraft:cherry_planks":4,"minecraft:soul_fire":2,"minecraft:crafting_table":7,"minecraft:torch":8,"minecraft:sculk_sensor":1,"minecraft:copper_ore":7,"minecraft:tall_grass":11,"minecraft:cobblestone":7,"minecraft:oak_planks":44,"minecraft:deepslate_coal_ore":29,"minecraft:deepslate_gold_ore":60,"minecraft:lapis_ore":23,"minecraft:sugar_cane":108,"minecraft:cracked_deepslate_bricks":1,"minecraft:diorite":481,"minecraft:wall_torch":12,"minecraft:warped_wart_block":1,"minecraft:pink_petals":8,"minecraft:birch_log":149,"minecraft:wheat":68,"minecraft:sweet_berry_bush":4,"minecraft:stone_brick_stairs":9,"minecraft:grass":61,"minecraft:oak_log":355,"minecraft:coal_ore":431,"minecraft:cherry_leaves":2,"minecraft:sand":69,"minecraft:gravel":18,"minecraft:dripstone_block":12,"minecraft:dirt":50,"minecraft:cobweb":9,"minecraft:stone_bricks":78,"minecraft:gold_ore":46,"minecraft:oak_leaves":10,"minecraft:deepslate":105,"minecraft:redstone_lamp":1},"minecraft:custom":{"minecraft:interact_with_anvil":3,"minecraft:mob_kills":66,"minecraft:animals_bred":3,"minecraft:interact_with_crafting_table":91,"minecraft:open_barrel":1,"minecraft:bell_ring":2,"minecraft:leave_game":25,"minecraft:time_since_death":420671,"minecraft:climb_one_cm":911,"minecraft:sprint_one_cm":1148859,"minecraft:walk_one_cm":1702596,"minecraft:damage_blocked_by_shield":2593,"minecraft:drop":58,"minecraft:talked_to_villager":3,"minecraft:play_time":552641,"minecraft:deaths":5,"minecraft:sneak_time":40120,"minecraft:walk_under_water_one_cm":68916,"minecraft:boat_one_cm":9945,"minecraft:jump":9057,"minecraft:walk_on_water_one_cm":63155,"minecraft:enchant_item":9,"minecraft:total_world_time":552641,"minecraft:interact_with_furnace":243,"minecraft:interact_with_stonecutter":4,"minecraft:sleep_in_bed":26,"minecraft:time_since_rest":1848,"minecraft:damage_taken":6982,"minecraft:damage_dealt":27654,"minecraft:swim_one_cm":64215,"minecraft:fly_one_cm":1884096,"minecraft:open_chest":202,"minecraft:crouch_one_cm":143431,"minecraft:fall_one_cm":282804,"minecraft:use_cauldron":1,"minecraft:horse_one_cm":3418886},"minecraft:killed":{"minecraft:spider":8,"minecraft:skeleton":22,"minecraft:pillager":1,"minecraft:zombie":25,"minecraft:blaze":2,"minecraft:enderman":2,"minecraft:cow":6},"minecraft:broken":{"minecraft:iron_shovel":2,"minecraft:iron_axe":2,"minecraft:stone_axe":1,"minecraft:iron_sword":2,"minecraft:iron_pickaxe":8},"minecraft:picked_up":{"minecraft:fishing_rod":1,"minecraft:crafting_table":7,"minecraft:wheat":55,"minecraft:redstone_lamp":1,"minecraft:gold_block":4,"minecraft:stone_brick_stairs":9,"minecraft:string":38,"minecraft:raw_copper":24,"minecraft:candle":30,"minecraft:cobbled_deepslate":115,"minecraft:beef":11,"minecraft:written_book":1,"minecraft:iron_pickaxe":1,"minecraft:sugar_cane":177,"minecraft:birch_sapling":7,"minecraft:egg":1,"minecraft:stick":33,"minecraft:raw_iron":594,"minecraft:stone":256,"minecraft:cherry_stairs":2,"minecraft:copper_ingot":4,"minecraft:torch":14,"minecraft:cherry_log":105,"minecraft:pointed_dripstone":21,"minecraft:diorite":588,"minecraft:carrot":74,"minecraft:redstone":87,"minecraft:stone_sword":1,"minecraft:arrow":46,"minecraft:rotten_flesh":70,"minecraft:nether_bricks":11,"minecraft:deepslate_bricks":2,"minecraft:hay_block":31,"minecraft:blaze_rod":36,"minecraft:obsidian":9,"minecraft:cobblestone":1057,"minecraft:birch_log":151,"minecraft:enchanting_table":1,"minecraft:pink_petals":23,"minecraft:cooked_beef":1,"minecraft:cherry_planks":31,"minecraft:cherry_leaves":22,"minecraft:andesite":12,"minecraft:leather":3,"minecraft:flint":3,"minecraft:oak_log":360,"minecraft:dirt":572,"minecraft:cherry_door":1,"minecraft:lapis_lazuli":202,"minecraft:bone":50,"minecraft:apple":8,"minecraft:stone_bricks":76,"minecraft:bow":3,"minecraft:wheat_seeds":205,"minecraft:raw_gold":125,"minecraft:iron_ingot":1,"minecraft:oak_planks":44,"minecraft:oak_slab":5,"minecraft:sweet_berries":22,"minecraft:sand":69,"minecraft:lava_bucket":1,"minecraft:oak_pressure_plate":1,"minecraft:gravel":16,"minecraft:dripstone_block":3,"minecraft:white_bed":7,"minecraft:barrel":4,"minecraft:jungle_slab":1,"minecraft:spider_eye":17,"minecraft:polished_diorite":5,"minecraft:diamond":2,"minecraft:granite":3,"minecraft:cherry_sapling":1,"minecraft:bread":26,"minecraft:oak_sapling":74,"minecraft:chorus_fruit":20,"minecraft:coal":498,"minecraft:ender_pearl":5}},"DataVersion":3465}